README.md
setup.cfg
setup.py
wwpdb/__init__.py
wwpdb.apps.seqmodule.egg-info/PKG-INFO
wwpdb.apps.seqmodule.egg-info/SOURCES.txt
wwpdb.apps.seqmodule.egg-info/dependency_links.txt
wwpdb.apps.seqmodule.egg-info/not-zip-safe
wwpdb.apps.seqmodule.egg-info/requires.txt
wwpdb.apps.seqmodule.egg-info/top_level.txt
wwpdb/apps/__init__.py
wwpdb/apps/seqmodule/__init__.py
wwpdb/apps/seqmodule/align/AlignmentBackEndEditingTools.py
wwpdb/apps/seqmodule/align/AlignmentDepictionTools.py
wwpdb/apps/seqmodule/align/AlignmentExport.py
wwpdb/apps/seqmodule/align/AlignmentFrontEndUIEditor.py
wwpdb/apps/seqmodule/align/AlignmentStatistics.py
wwpdb/apps/seqmodule/align/AlignmentStatisticsTests.py
wwpdb/apps/seqmodule/align/AlignmentToolUtils.py
wwpdb/apps/seqmodule/align/AlignmentTools.py
wwpdb/apps/seqmodule/align/__init__.py
wwpdb/apps/seqmodule/control/DataImporter.py
wwpdb/apps/seqmodule/control/SequenceDataAssembleExample.py
wwpdb/apps/seqmodule/control/SequenceDataAssembleTests.py
wwpdb/apps/seqmodule/control/SequenceDataAssemble_v2.py
wwpdb/apps/seqmodule/control/SequenceDataPrepTests.py
wwpdb/apps/seqmodule/control/SummaryViewDepiction.py
wwpdb/apps/seqmodule/control/SummaryViewTests.py
wwpdb/apps/seqmodule/control/SummaryView_v2.py
wwpdb/apps/seqmodule/control/__init__.py
wwpdb/apps/seqmodule/io/AlignmentDataStore.py
wwpdb/apps/seqmodule/io/BlastPlusReader.py
wwpdb/apps/seqmodule/io/FetchSeqInfoUtils.py
wwpdb/apps/seqmodule/io/ModelSequenceUtils.py
wwpdb/apps/seqmodule/io/ModelSequenceUtilsTests.py
wwpdb/apps/seqmodule/io/PdbxIoUtils.py
wwpdb/apps/seqmodule/io/SequenceDataExportTests.py
wwpdb/apps/seqmodule/io/SequenceDataExport_v2.py
wwpdb/apps/seqmodule/io/SequenceDataStore.py
wwpdb/apps/seqmodule/io/SequenceDataStoreTests.py
wwpdb/apps/seqmodule/io/SequenceEditStore.py
wwpdb/apps/seqmodule/io/SequenceEditStoreTests.py
wwpdb/apps/seqmodule/io/TaxonomyDbUtils.py
wwpdb/apps/seqmodule/io/TaxonomyUtils.py
wwpdb/apps/seqmodule/io/TaxonomyUtilsTests.py
wwpdb/apps/seqmodule/io/__init__.py
wwpdb/apps/seqmodule/io/testAuto.py
wwpdb/apps/seqmodule/link/PolymerLinkageDepict.py
wwpdb/apps/seqmodule/link/__init__.py
wwpdb/apps/seqmodule/update/UpdatePolymerEntityPartitions.py
wwpdb/apps/seqmodule/update/UpdatePolymerEntityReference_v2.py
