Metadata-Version: 2.1
Name: wwpdb.apps.seqmodule
Version: 0.26.9
Summary: wwPDB sequence module
Home-page: https://github.com/wwPDB/py-wwpdb_apps_seqmodule
Author: Ezra Peisach
Author-email: ezra.peisach@rcsb.org
License: Apache 2.0
Classifier: Development Status :: 3 - Alpha
Classifier: Intended Audience :: Developers
Classifier: Natural Language :: English
Classifier: License :: OSI Approved :: Apache Software License
Classifier: Programming Language :: Python
Classifier: Programming Language :: Python :: 2.7
Classifier: Programming Language :: Python :: 3
Classifier: Programming Language :: Python :: 3.6
Classifier: Programming Language :: Python :: 3.7
Requires-Dist: wwpdb.utils.config>=0.33
Requires-Dist: wwpdb.io>=0.27
Requires-Dist: wwpdb.utils.session>=0.14
Requires-Dist: wwpdb.utils.wf>=0.30
Requires-Dist: wwpdb.utils.seqdb_v2~=0.11
Requires-Dist: wwpdb.utils.align>=0.11
Requires-Dist: wwpdb.utils.detach>=0.4.2
Requires-Dist: wwpdb.utils.dp~=0.48
Requires-Dist: wwpdb.utils.db>=0.28
Requires-Dist: rcsb.utils.multiproc
Provides-Extra: dev
Requires-Dist: check-manifest; extra == "dev"
Provides-Extra: test
Requires-Dist: coverage; extra == "test"
